ximo_statstools/Binomialdistribution.py
ximo_statstools/Gaussiandistribution.py
ximo_statstools/Generaldistribution.py
ximo_statstools/__init__.py
ximo_statstools-0.1.dist-info/DESCRIPTION.rst
ximo_statstools-0.1.dist-info/METADATA
ximo_statstools-0.1.dist-info/RECORD
ximo_statstools-0.1.dist-info/WHEEL
ximo_statstools-0.1.dist-info/metadata.json
ximo_statstools-0.1.dist-info/top_level.txt
