Metadata-Version: 2.0
Name: ximo-statstools
Version: 0.1
Summary: Statistics tools by Ximo!
Home-page: UNKNOWN
Author: UNKNOWN
Author-email: UNKNOWN
License: UNKNOWN
Platform: UNKNOWN
